{
  "hash": "3650176f",
  "browserHash": "4004d0d7",
  "optimized": {
    "vue": {
      "src": "../../../../../../node_modules/.pnpm/registry.npmmirror.com+vue@3.2.36/node_modules/vue/dist/vue.runtime.esm-bundler.js",
      "file": "vue.js",
      "fileHash": "3c8c2219",
      "needsInterop": false
    },
    "@theme/index": {
      "src": "../../../../../../node_modules/.pnpm/registry.npmmirror.com+vitepress@1.0.0-alpha.48/node_modules/vitepress/dist/client/theme-default/index.js",
      "file": "@theme_index.js",
      "fileHash": "0625b5a0",
      "needsInterop": false
    }
  },
  "chunks": {}
}